ChocoRocket/__init__.py
ChocoRocket/main.py
ChocoRocket/model.py
ChocoRocket/images/bg.png
ChocoRocket/images/choco.png
ChocoRocket/images/meteor.png
ChocoRocket/images/p1.png
choco_rocket/__init__.py
choco_rocket/main.py
choco_rocket-0.2.2.dist-info/LICENSE
choco_rocket-0.2.2.dist-info/METADATA
choco_rocket-0.2.2.dist-info/WHEEL
choco_rocket-0.2.2.dist-info/entry_points.txt
choco_rocket-0.2.2.dist-info/top_level.txt
choco_rocket-0.2.2.dist-info/RECORD
