Metadata-Version: 2.1
Name: choco-rocket
Version: 0.2.2
Summary: Arcade Game with an Astronaut and his Rocket
Home-page: https://github.com/joseaorufino/choco-rocket
Author: Jose Augusto O. Rufino
Author-email: joseaorufino@gmail.com
License: UNKNOWN
Platform: UNKNOWN
Classifier: Programming Language :: Python :: 3
Classifier: License :: OSI Approved :: MIT License
Classifier: Operating System :: OS Independent
Requires-Python: >=3.6
Requires-Dist: pygame
